rainiee_decision_engine_test/__init__.py
rainiee_decision_engine_test/common_client.py
rainiee_decision_engine_test/decision_engine_client.py
rainiee_decision_engine_test/base/__init__.py
rainiee_decision_engine_test/base/client.py
rainiee_decision_engine_test/base/data_pro.py
rainiee_decision_engine_test/base/login.py
rainiee_decision_engine_test/portfolio/__init__.py
rainiee_decision_engine_test/portfolio/portfolio_api.py
rainiee_decision_engine_test/utils/__init__.py
rainiee_decision_engine_test/utils/upass.py
rainiee_decision_engine_test-2.2.0.dist-info/METADATA
rainiee_decision_engine_test-2.2.0.dist-info/WHEEL
rainiee_decision_engine_test-2.2.0.dist-info/top_level.txt
rainiee_decision_engine_test-2.2.0.dist-info/RECORD
